setup.py
adapters/__init__.py
adapters/context_adapter.py
adapters/extension.py
aria_extension_cloudify.egg-info/PKG-INFO
aria_extension_cloudify.egg-info/SOURCES.txt
aria_extension_cloudify.egg-info/dependency_links.txt
aria_extension_cloudify.egg-info/entry_points.txt
aria_extension_cloudify.egg-info/requires.txt
aria_extension_cloudify.egg-info/top_level.txt