Metadata-Version: 1.0
Name: aria-extension-cloudify
Version: 4.2
Summary: Enable ARIA to utilize some of Cloudify's abilities, such as interfacing with AWS and Openstack.
Home-page: UNKNOWN
Author: Gigaspaces
Author-email: cosmo-admin@gigaspaces.com
License: LICENSE
Platform: UNKNOWN
